softserved.py
softserved-1.1.3.dist-info/licenses/LICENSE
softserved-1.1.3.dist-info/METADATA
softserved-1.1.3.dist-info/WHEEL
softserved-1.1.3.dist-info/entry_points.txt
softserved-1.1.3.dist-info/top_level.txt
softserved-1.1.3.dist-info/RECORD
