Metadata-Version: 2.4
Name: softserved
Version: 1.1.3
Summary: A lightweight, stylish local web server for static files
Home-page: https://github.com/tolaoyelola/softserved
Author: Tola Oyelola
Author-email: tola@ootola.com
Classifier: Programming Language :: Python :: 3
Classifier: License :: OSI Approved :: MIT License
Classifier: Operating System :: OS Independent
Classifier: Development Status :: 4 - Beta
Classifier: Intended Audience :: Developers
Classifier: Topic :: Internet :: WWW/HTTP :: HTTP Servers
Requires-Python: >=3.6
License-File: LICENSE
Requires-Dist: colorama>=0.4.3
Requires-Dist: watchdog>=3.0.0
Dynamic: author
Dynamic: author-email
Dynamic: classifier
Dynamic: description
Dynamic: description-content-type
Dynamic: home-page
Dynamic: license-file
Dynamic: requires-dist
Dynamic: requires-python
Dynamic: summary
